{"container_type": "Author", "filled": ["basics", "publications", "indices", "counts"], "scholar_id": "w_KlCEkAAAAJ", "source": "AUTHOR_PROFILE_PAGE", "name": "Ronghua Li", "affiliation": "PolyU", "interests": ["IoT network security", "ML"], "email_domain": "@connect.polyu.hk", "citedby": 27, "publications": {"w_KlCEkAAAAJ:u5HHmVD_uO8C": {"container_type": "Publication", "source": "AUTHOR_PUBLICATION_ENTRY", "bib": {"title": "RFTrack: Stealthy location inference and tracking attack on Wi-Fi devices", "pub_year": "2024"}, "filled": false, "author_pub_id": "w_KlCEkAAAAJ:u5HHmVD_uO8C", "num_citations": 18, "citedby_url": "https://scholar.google.com/scholar?oi=bibs&hl=en&cites=15362186872217330209", "cites_id": ["15362186872217330209"]}, "w_KlCEkAAAAJ:u-x6o8ySG0sC": {"container_type": "Publication", "source": "AUTHOR_PUBLICATION_ENTRY", "bib": {"title": "Alignment-aware model extraction attacks on large language models", "pub_year": "2024"}, "filled": false, "author_pub_id": "w_KlCEkAAAAJ:u-x6o8ySG0sC", "num_citations": 7, "citedby_url": "https://scholar.google.com/scholar?oi=bibs&hl=en&cites=13345430769771273671", "cites_id": ["13345430769771273671"]}, "w_KlCEkAAAAJ:qjMakFHDy7sC": {"container_type": "Publication", "source": "AUTHOR_PUBLICATION_ENTRY", "bib": {"title": "“Yes, My LoRD.” Guiding Language Model Extraction with Locality Reinforced Distillation", "pub_year": "2025"}, "filled": false, "author_pub_id": "w_KlCEkAAAAJ:qjMakFHDy7sC", "num_citations": 2, "citedby_url": "https://scholar.google.com/scholar?oi=bibs&hl=en&cites=2914913582369788181", "cites_id": ["2914913582369788181"]}, "w_KlCEkAAAAJ:2osOgNQ5qMEC": {"container_type": "Publication", "source": "AUTHOR_PUBLICATION_ENTRY", "bib": {"title": "Class-feature Watermark: A Resilient Black-box Watermark Against Model Extraction Attacks", "pub_year": "2025"}, "filled": false, "author_pub_id": "w_KlCEkAAAAJ:2osOgNQ5qMEC", "num_citations": 0}, "w_KlCEkAAAAJ:d1gkVwhDpl0C": {"container_type": "Publication", "source": "AUTHOR_PUBLICATION_ENTRY", "bib": {"title": "WiFinger: Fingerprinting Noisy IoT Event Traffic Using Packet-level Sequence Matching", "pub_year": "2025"}, "filled": false, "author_pub_id": "w_KlCEkAAAAJ:d1gkVwhDpl0C", "num_citations": 0}}, "citedby5y": 27, "hindex": 2, "hindex5y": 2, "i10index": 1, "i10index5y": 1, "cites_per_year": {"2024": 2, "2025": 25}, "updated": "2026-01-10 16:43:40.310351"}